Workbook

Sheet Assumptions
B2: Build vs. Buy — TCO Model | Assumptions & Inputs
B3: Yellow cells are inputs — replace with real figures. Each input is also a question to ask.
B5: GLOBAL | C5: Value | D5: Question this input drives
B6: Analysis horizon (years) | C6: 5 | D6: Over how many years should we compare? (TCO differences show over time)
B7: Annual discount rate (%) | C7: 0.08 | D7: What rate should we use for present value? (cost of capital)
B8: Annual transaction / claim volume | C8: 2000000 | D8: What volume are we processing today, and projected growth?
B10: BUILD (In-House) | C10: Value | D10: Question this input drives
B11: Upfront development cost (one-time) | C11: 600000 | D11: What will it cost to build? (dev hours x rate, or MSP/contractor cost)
B12: Implementation / integration (one-time) | C12: 120000 | D12: Integration, testing, migration effort to go live?
B13: Annual internal labor (run/maintain) | C13: 180000 | D13: FTEs to maintain & support once live, fully loaded?
B14: Annual infrastructure / cloud | C14: 60000 | D14: Hosting, compute, storage, monitoring per year?
B15: Annual enhancements / change | C15: 80000 | D15: Ongoing dev to keep pace with mandates & changes?
B16: Time to deploy (months) | C16: 12 | D16: How long until it's in production? (delay = risk & carry cost)
B18: BUY (Vendor / Edifecs) | C18: Value | D18: Question this input drives
B19: Annual license / subscription | C19: 350000 | D19: What's the annual license fee, and how does it escalate?
B20: Implementation / onboarding (one-time) | C20: 200000 | D20: One-time setup, config, and integration cost?
B21: Annual vendor support / maintenance | C21: 70000 | D21: Support/maintenance tier and cost per year?
B22: Per-transaction / volume fees (annual) | C22: 40000 | D22: Any per-transaction or volume-based charges?
B23: Annual internal labor (vendor mgmt) | C23: 60000 | D23: Internal effort to manage the vendor & integration?
B24: Time to deploy (months) | C24: 4 | D24: How fast can the vendor get us live?

Sheet TCO Comparison
B2: Build vs. Buy — Year-by-Year TCO
B3: All figures pull from the Assumptions tab. Nominal dollars; PV summary below.
B5: Cost Category | C5: Year 1 | D5: Year 2 | E5: Year 3 | F5: Year 4 | G5: Year 5 | H5: 5-Yr Total
B6: BUILD (In-House)
B7: Annual build cost | C7: =Assumptions!C11+Assumptions!C12+Assumptions!C13+Assumptions!C14+Assumptions!C15 -> 1040000 | D7: =Assumptions!C13+Assumptions!C14+Assumptions!C15 -> 320000 | E7: =Assumptions!C13+Assumptions!C14+Assumptions!C15 -> 320000 | F7: =Assumptions!C13+Assumptions!C14+Assumptions!C15 -> 320000 | G7: =Assumptions!C13+Assumptions!C14+Assumptions!C15 -> 320000 | H7: =SUM(C7:G7) -> 2320000
B9: BUY (Vendor / Edifecs)
B10: Annual buy cost | C10: =Assumptions!C19+Assumptions!C20+Assumptions!C21+Assumptions!C22+Assumptions!C23 -> 720000 | D10: =Assumptions!C19+Assumptions!C21+Assumptions!C22+Assumptions!C23 -> 520000 | E10: =Assumptions!C19+Assumptions!C21+Assumptions!C22+Assumptions!C23 -> 520000 | F10: =Assumptions!C19+Assumptions!C21+Assumptions!C22+Assumptions!C23 -> 520000 | G10: =Assumptions!C19+Assumptions!C21+Assumptions!C22+Assumptions!C23 -> 520000 | H10: =SUM(C10:G10) -> 2800000
B12: Cumulative BUILD | C12: =C7 -> 1040000 | D12: =C12+D7 -> 1360000 | E12: =D12+E7 -> 1680000 | F12: =E12+F7 -> 2000000 | G12: =F12+G7 -> 2320000
B13: Cumulative BUY | C13: =C10 -> 720000 | D13: =C13+D10 -> 1240000 | E13: =D13+E10 -> 1760000 | F13: =E13+F10 -> 2280000 | G13: =F13+G10 -> 2800000
B15: Annual difference (Buy - Build) | C15: =C10-C7 -> -320000 | D15: =D10-D7 -> 200000 | E15: =E10-E7 -> 200000 | F15: =F10-F7 -> 200000 | G15: =G10-G7 -> 200000 | H15: =H10-H7 -> 480000
B16: (positive = Build is cheaper that year)

Sheet Summary
B2: Build vs. Buy — Decision Summary
B4: Metric | C4: Result | D4: Notes
B5: Total 5-Yr Cost — BUILD | C5: ='TCO Comparison'!H7 -> 2320000 | D5: Upfront-heavy; cost front-loaded in Year 1.
B6: Total 5-Yr Cost — BUY | C6: ='TCO Comparison'!H10 -> 2800000 | D6: Smoother; recurring license each year.
B7: 5-Yr Savings (Buy - Build) | C7: =C6-C5 -> 480000 | D7: Positive = Build cheaper over horizon.
B8: Lower-TCO option | C8: =IF(C5<C6,"BUILD","BUY") -> BUILD | D8: Numeric winner only — weigh against qualitative factors below.
B9: Deploy speed advantage | C9: =IF(Assumptions!C16>Assumptions!C24,"BUY faster","BUILD faster") -> BUY faster | D9: Time-to-deploy gap = risk, carry cost, opportunity cost.
B11: QUALITATIVE FACTORS (score 1-5 each) | C11: Build / Buy | D11: Question to ask
B12: Control & customization | C12: Build | D12: How much do we need to tailor beyond what a vendor allows?
B13: Speed to value | C13: Buy | D13: How urgently do we need this live?
B14: Vendor lock-in risk | C14: Build | D14: How hard/costly to switch or exit the vendor later?
B15: Internal capability / bandwidth | C15: ? | D15: Do we have the team to build AND sustain it?
B16: Compliance & mandate agility | C16: ? | D16: Who adapts faster to CMS/state mandate changes?
B17: Strategic differentiation | C17: ? | D17: Is this core IP worth owning, or a commodity to rent?
B19: Recommendation:
B20: (Document the decision, the reasoning, and the reassessment trigger — e.g. 'build in-house first to standardize; revisit vendor analytics tooling once volume/《needs》 are proven.')
